semantic_chunker_langchain/__init__.py
semantic_chunker_langchain/chunker.py
semantic_chunker_langchain/extractors/pdf.py
semantic_chunker_langchain/outputs/formatter.py
semantic_chunker_langchain/utils.py
semantic_chunker_langchain-0.1.4.dist-info/entry_points.txt
semantic_chunker_langchain-0.1.4.dist-info/LICENSE
semantic_chunker_langchain-0.1.4.dist-info/METADATA
semantic_chunker_langchain-0.1.4.dist-info/WHEEL
semantic_chunker_langchain-0.1.4.dist-info/RECORD
