Metadata-Version: 2.3
Name: semantic-chunker-langchain
Version: 0.1.4
Summary: Token-aware, LangChain-compatible semantic chunker with PDF and layout support
License: MIT
Author: Prajwal Shivaji Mandale
Author-email: prajwal.mandale333@gmail.com
Requires-Python: >=3.9,<3.13
Classifier: License :: OSI Approved :: MIT License
Classifier: Programming Language :: Python :: 3
Classifier: Programming Language :: Python :: 3.9
Classifier: Programming Language :: Python :: 3.10
Classifier: Programming Language :: Python :: 3.11
Classifier: Programming Language :: Python :: 3.12
Requires-Dist: faiss-cpu (>=1.11.0,<2.0.0)
Requires-Dist: langchain (>=0.3.25,<0.4.0)
Requires-Dist: langchain-community (>=0.3.26,<0.4.0)
Requires-Dist: openai (>=1.84.0,<2.0.0)
Requires-Dist: pdfplumber (>=0.11.6,<0.12.0)
Requires-Dist: tiktoken (>=0.9.0,<0.10.0)
